vcheck/__init__.py
vcheck/checkmod.py
vcheck/scripts.py
vcheck/vcheckmod.py
vcheck/versionerror.py
vcheck/versionmod.py
VCheck-1.6.1.dist-info/top_level.txt
VCheck-1.6.1.dist-info/entry_points.txt
VCheck-1.6.1.dist-info/METADATA
VCheck-1.6.1.dist-info/DESCRIPTION.rst
VCheck-1.6.1.dist-info/metadata.json
VCheck-1.6.1.dist-info/WHEEL
VCheck-1.6.1.dist-info/RECORD
