Metadata-Version: 2.0
Name: VCheck
Version: 1.6.1
Summary: Version checking for Python modules
Home-page: https://github.com/joelfrederico/VCheck
Author: Joel Frederico, SLAC National Accelerator Laboratory
Author-email: joelfred@slac.stanford.edu
License: MIT
Keywords: version check test development quality assurance
Platform: UNKNOWN
Classifier: Development Status :: 3 - Alpha
Classifier: Intended Audience :: Developers
Classifier: Topic :: Software Development :: Quality Assurance
Classifier: Topic :: Software Development :: Testing
Classifier: License :: OSI Approved :: MIT License
Classifier: Programming Language :: Python :: 3
Classifier: Programming Language :: Python :: 3.5
Requires-Dist: gitpython
Requires-Dist: numpydoc
